push/__init__.py
push/batteries.py
push/code_utils.py
push/host_resources.py
push/push_manager.py
push/push_repl.py
push/push_server.py
push/push_server_utils.py
push/task_manager.py
pushpy/__init__.py
pushpy/batteries.py
pushpy/code_utils.py
pushpy/host_resources.py
pushpy/push_manager.py
pushpy/push_repl.py
pushpy/push_server.py
pushpy/push_server_utils.py
pushpy/task_manager.py
pushpy_examples/__init__.py
pushpy_examples/batteries.py
pushpy_examples/ex_boot.py
pushpy_examples/ex_push_manager.py
pushpy_examples/simple_interpreter.py
pushpy-0.1.1.dist-info/LICENSE.txt
pushpy-0.1.1.dist-info/METADATA
pushpy-0.1.1.dist-info/WHEEL
pushpy-0.1.1.dist-info/entry_points.txt
pushpy-0.1.1.dist-info/top_level.txt
pushpy-0.1.1.dist-info/RECORD
